LICENSE.txt
MANIFEST.in
README
README.rst
requirements.txt
setup.py
test_requirements.txt
cloudlib/__init__.py
cloudlib/arguments.py
cloudlib/http.py
cloudlib/indicator.py
cloudlib/logger.py
cloudlib/mail.py
cloudlib/package_installer.py
cloudlib/parse_ini.py
cloudlib/shell.py
cloudlib/utils.py
cloudlib.egg-info/PKG-INFO
cloudlib.egg-info/SOURCES.txt
cloudlib.egg-info/dependency_links.txt
cloudlib.egg-info/pbr.json
cloudlib.egg-info/requires.txt
cloudlib.egg-info/top_level.txt
docs/Makefile
docs/cloudlib.1
docs/cloudlib.rst
docs/cloudlib.tests.rst
docs/conf.py
docs/index.rst
docs/make.bat
docs/modules.rst
docs/undoc.pickle
docs/_build/doctest/output.txt
docs/_build/doctrees/cloudlib.doctree
docs/_build/doctrees/cloudlib.tests.doctree
docs/_build/doctrees/environment.pickle
docs/_build/doctrees/index.doctree
docs/_build/doctrees/modules.doctree